<?xml version="1.0" encoding="UTF-8" standalone="yes"?>
<w:document xmlns:wpc="http://schemas.microsoft.com/office/word/2010/wordprocessingCanvas" xmlns:mc="http://schemas.openxmlformats.org/markup-compatibility/2006" xmlns:o="urn:schemas-microsoft-com:office:office" xmlns:r="http://schemas.openxmlformats.org/officeDocument/2006/relationships" xmlns:m="http://schemas.openxmlformats.org/officeDocument/2006/math" xmlns:v="urn:schemas-microsoft-com:vml" xmlns:wp14="http://schemas.microsoft.com/office/word/2010/wordprocessingDrawing" xmlns:wp="http://schemas.openxmlformats.org/drawingml/2006/wordprocessingDrawing" xmlns:w="http://schemas.openxmlformats.org/wordprocessingml/2006/main" xmlns:w14="http://schemas.microsoft.com/office/word/2010/wordml" xmlns:w10="urn:schemas-microsoft-com:office:word" xmlns:w15="http://schemas.microsoft.com/office/word/2012/wordml" xmlns:wpg="http://schemas.microsoft.com/office/word/2010/wordprocessingGroup" xmlns:wpi="http://schemas.microsoft.com/office/word/2010/wordprocessingInk" xmlns:wne="http://schemas.microsoft.com/office/word/2006/wordml" xmlns:wps="http://schemas.microsoft.com/office/word/2010/wordprocessingShape" xmlns:wpsCustomData="http://www.wps.cn/officeDocument/2013/wpsCustomData" mc:Ignorable="w14 w15 wp14"><w:body><w:p w14:paraId="1D1694B3"><w:pPr><w:pStyle w:val="2"/><w:keepNext w:val="0"/><w:keepLines w:val="0"/><w:widowControl/><w:suppressLineNumbers w:val="0"/><w:pBdr><w:bottom w:val="none" w:color="auto" w:sz="0" w:space="0"/></w:pBdr><w:shd w:val="clear" w:fill="FFFFFF"/><w:spacing w:before="0" w:beforeAutospacing="0" w:line="13" w:lineRule="atLeast"/><w:ind w:left="0" w:right="0" w:firstLine="0"/><w:jc w:val="center"/><w:rPr><w:rFonts w:hint="eastAsia" w:ascii="宋体" w:hAnsi="宋体" w:eastAsia="宋体" w:cs="宋体"/><w:i w:val="0"/><w:iCs w:val="0"/><w:caps w:val="0"/><w:color w:val="1F2328"/><w:spacing w:val="0"/><w:sz w:val="44"/><w:szCs w:val="44"/></w:rPr></w:pPr><w:r><w:rPr><w:rFonts w:hint="eastAsia" w:ascii="宋体" w:hAnsi="宋体" w:eastAsia="宋体" w:cs="宋体"/><w:i w:val="0"/><w:iCs w:val="0"/><w:caps w:val="0"/><w:color w:val="1F2328"/><w:spacing w:val="0"/><w:sz w:val="44"/><w:szCs w:val="44"/><w:shd w:val="clear" w:fill="FFFFFF"/></w:rPr><w:t>深度学习与神经网络</w:t></w:r><w:r><w:rPr><w:rFonts w:hint="eastAsia" w:ascii="宋体" w:hAnsi="宋体" w:eastAsia="宋体" w:cs="宋体"/><w:i w:val="0"/><w:iCs w:val="0"/><w:caps w:val="0"/><w:color w:val="1F2328"/><w:spacing w:val="0"/><w:sz w:val="44"/><w:szCs w:val="44"/><w:shd w:val="clear" w:fill="FFFFFF"/><w:lang w:val="en-US" w:eastAsia="zh-CN"/></w:rPr><w:t>第三次作业</w:t></w:r></w:p><w:p w14:paraId="1140C1F3"><w:pPr><w:keepNext w:val="0"/><w:keepLines w:val="0"/><w:pageBreakBefore w:val="0"/><w:widowControl w:val="0"/><w:numPr><w:ilvl w:val="0"/><w:numId w:val="1"/></w:numPr><w:kinsoku/><w:wordWrap/><w:overflowPunct/><w:topLinePunct w:val="0"/><w:autoSpaceDE/><w:autoSpaceDN/><w:bidi w:val="0"/><w:adjustRightInd/><w:snapToGrid/><w:spacing w:before="157" w:beforeLines="50" w:after="157" w:afterLines="50"/><w:ind w:left="-480" w:leftChars="0" w:firstLine="480" w:firstLineChars="0"/><w:textAlignment w:val="auto"/><w:rPr><w:rFonts w:hint="eastAsia" w:ascii="宋体" w:hAnsi="宋体" w:eastAsia="宋体" w:cs="宋体"/><w:b/><w:bCs/><w:sz w:val="24"/><w:szCs w:val="24"/><w:lang w:val="en-US" w:eastAsia="zh-CN"/></w:rPr></w:pPr><w:r><w:rPr><w:rFonts w:hint="eastAsia" w:ascii="宋体" w:hAnsi="宋体" w:eastAsia="宋体" w:cs="宋体"/><w:b/><w:bCs/><w:sz w:val="24"/><w:szCs w:val="24"/><w:lang w:val="en-US" w:eastAsia="zh-CN"/></w:rPr><w:t>解释RNN、LSTM、GRU模型</w:t></w:r></w:p><w:p w14:paraId="55F35D85"><w:pPr><w:keepNext w:val="0"/><w:keepLines w:val="0"/><w:pageBreakBefore w:val="0"/><w:widowControl w:val="0"/><w:numPr><w:ilvl w:val="1"/><w:numId w:val="1"/></w:numPr><w:kinsoku/><w:wordWrap/><w:overflowPunct/><w:topLinePunct w:val="0"/><w:autoSpaceDE/><w:autoSpaceDN/><w:bidi w:val="0"/><w:adjustRightInd/><w:snapToGrid/><w:spacing w:before="157" w:beforeLines="50" w:after="157" w:afterLines="50"/><w:ind w:left="-60" w:leftChars="0" w:firstLine="480" w:firstLineChars="0"/><w:textAlignment w:val="auto"/><w:rPr><w:rFonts w:hint="eastAsia" w:ascii="宋体" w:hAnsi="宋体" w:eastAsia="宋体" w:cs="宋体"/><w:b/><w:bCs/><w:sz w:val="21"/><w:szCs w:val="21"/><w:lang w:val="en-US" w:eastAsia="zh-CN"/></w:rPr></w:pPr><w:r><w:rPr><w:rFonts w:hint="eastAsia" w:ascii="宋体" w:hAnsi="宋体" w:eastAsia="宋体" w:cs="宋体"/><w:b/><w:bCs/><w:sz w:val="21"/><w:szCs w:val="21"/><w:lang w:val="en-US" w:eastAsia="zh-CN"/></w:rPr><w:t>RNN</w:t></w:r></w:p><w:p w14:paraId="59859856"><w:pPr><w:keepNext w:val="0"/><w:keepLines w:val="0"/><w:pageBreakBefore w:val="0"/><w:widowControl w:val="0"/><w:kinsoku/><w:wordWrap/><w:overflowPunct/><w:topLinePunct w:val="0"/><w:autoSpaceDE/><w:autoSpaceDN/><w:bidi w:val="0"/><w:adjustRightInd/><w:snapToGrid/><w:spacing w:before="157" w:beforeLines="50" w:after="157" w:afterLines="50"/><w:ind w:left="0" w:firstLine="422" w:firstLineChars="200"/><w:textAlignment w:val="auto"/><w:rPr><w:rFonts w:hint="eastAsia" w:ascii="宋体" w:hAnsi="宋体" w:eastAsia="宋体" w:cs="宋体"/><w:sz w:val="21"/><w:szCs w:val="21"/><w:lang w:val="en-US" w:eastAsia="zh-CN"/></w:rPr></w:pPr><w:r><w:rPr><w:rFonts w:hint="eastAsia" w:ascii="宋体" w:hAnsi="宋体" w:eastAsia="宋体" w:cs="宋体"/><w:b/><w:bCs/><w:sz w:val="21"/><w:szCs w:val="21"/><w:lang w:val="en-US" w:eastAsia="zh-CN"/></w:rPr><w:t>定义：</w:t></w:r><w:r><w:rPr><w:rFonts w:hint="eastAsia" w:ascii="宋体" w:hAnsi="宋体" w:eastAsia="宋体" w:cs="宋体"/><w:sz w:val="21"/><w:szCs w:val="21"/><w:lang w:val="en-US" w:eastAsia="zh-CN"/></w:rPr><w:t>RNN (Recurrent Neural Network)是一种用于处理序列数据的神经网络模型。核心特性是能够保留并传递先前时间步的信息，从而可以对当前输入产生影响。因此RNN特别适用于时间序列数据或顺序数据（例如文本、音频等）。</w:t></w:r></w:p><w:p w14:paraId="0047CF08"><w:pPr><w:keepNext w:val="0"/><w:keepLines w:val="0"/><w:pageBreakBefore w:val="0"/><w:widowControl w:val="0"/><w:kinsoku/><w:wordWrap/><w:overflowPunct/><w:topLinePunct w:val="0"/><w:autoSpaceDE/><w:autoSpaceDN/><w:bidi w:val="0"/><w:adjustRightInd/><w:snapToGrid/><w:spacing w:before="157" w:beforeLines="50" w:after="157" w:afterLines="50"/><w:ind w:left="0" w:firstLine="422" w:firstLineChars="200"/><w:textAlignment w:val="auto"/><w:rPr><w:rFonts w:hint="eastAsia" w:ascii="宋体" w:hAnsi="宋体" w:eastAsia="宋体" w:cs="宋体"/><w:sz w:val="21"/><w:szCs w:val="21"/><w:lang w:val="en-US" w:eastAsia="zh-CN"/></w:rPr></w:pPr><w:r><w:rPr><w:rFonts w:hint="eastAsia" w:ascii="宋体" w:hAnsi="宋体" w:eastAsia="宋体" w:cs="宋体"/><w:b/><w:bCs/><w:sz w:val="21"/><w:szCs w:val="21"/><w:lang w:val="en-US" w:eastAsia="zh-CN"/></w:rPr><w:t>原理：</w:t></w:r><w:r><w:rPr><w:rFonts w:hint="eastAsia" w:ascii="宋体" w:hAnsi="宋体" w:eastAsia="宋体" w:cs="宋体"/><w:sz w:val="21"/><w:szCs w:val="21"/><w:lang w:val="en-US" w:eastAsia="zh-CN"/></w:rPr><w:t>RNN在每一个时间步骤中，通过循环结构将前一时刻的隐状态（hidden state）传递到当前时刻的输入中。这样，模型能够利用历史信息来影响当前的预测。RNN的基本思想是将前一个时间步的隐藏层输出作为下一个时间步的输入，形成一种“记忆”。</w:t></w:r></w:p><w:p w14:paraId="3909CFA1"><w:pPr><w:keepNext w:val="0"/><w:keepLines w:val="0"/><w:pageBreakBefore w:val="0"/><w:widowControl w:val="0"/><w:kinsoku/><w:wordWrap/><w:overflowPunct/><w:topLinePunct w:val="0"/><w:autoSpaceDE/><w:autoSpaceDN/><w:bidi w:val="0"/><w:adjustRightInd/><w:snapToGrid/><w:spacing w:before="157" w:beforeLines="50" w:after="157" w:afterLines="50"/><w:ind w:left="0" w:firstLine="422" w:firstLineChars="200"/><w:textAlignment w:val="auto"/><w:rPr><w:rFonts w:hint="eastAsia" w:ascii="宋体" w:hAnsi="宋体" w:eastAsia="宋体" w:cs="宋体"/><w:sz w:val="21"/><w:szCs w:val="21"/><w:lang w:val="en-US" w:eastAsia="zh-CN"/></w:rPr></w:pPr><w:r><w:rPr><w:rFonts w:hint="eastAsia" w:ascii="宋体" w:hAnsi="宋体" w:eastAsia="宋体" w:cs="宋体"/><w:b/><w:bCs/><w:sz w:val="21"/><w:szCs w:val="21"/><w:lang w:val="en-US" w:eastAsia="zh-CN"/></w:rPr><w:t>优点：</w:t></w:r><w:r><w:rPr><w:rFonts w:hint="eastAsia" w:ascii="宋体" w:hAnsi="宋体" w:eastAsia="宋体" w:cs="宋体"/><w:sz w:val="21"/><w:szCs w:val="21"/><w:lang w:val="en-US" w:eastAsia="zh-CN"/></w:rPr><w:t>适合处理序列数据，短期记忆能力。</w:t></w:r></w:p><w:p w14:paraId="37AEA398"><w:pPr><w:keepNext w:val="0"/><w:keepLines w:val="0"/><w:pageBreakBefore w:val="0"/><w:widowControl w:val="0"/><w:kinsoku/><w:wordWrap/><w:overflowPunct/><w:topLinePunct w:val="0"/><w:autoSpaceDE/><w:autoSpaceDN/><w:bidi w:val="0"/><w:adjustRightInd/><w:snapToGrid/><w:spacing w:before="157" w:beforeLines="50" w:after="157" w:afterLines="50"/><w:ind w:left="0" w:firstLine="422" w:firstLineChars="200"/><w:textAlignment w:val="auto"/><w:rPr><w:rFonts w:hint="eastAsia" w:ascii="宋体" w:hAnsi="宋体" w:eastAsia="宋体" w:cs="宋体"/><w:sz w:val="21"/><w:szCs w:val="21"/><w:lang w:val="en-US" w:eastAsia="zh-CN"/></w:rPr></w:pPr><w:r><w:rPr><w:rFonts w:hint="eastAsia" w:ascii="宋体" w:hAnsi="宋体" w:eastAsia="宋体" w:cs="宋体"/><w:b/><w:bCs/><w:sz w:val="21"/><w:szCs w:val="21"/><w:lang w:val="en-US" w:eastAsia="zh-CN"/></w:rPr><w:t>缺点：</w:t></w:r><w:r><w:rPr><w:rFonts w:hint="eastAsia" w:ascii="宋体" w:hAnsi="宋体" w:eastAsia="宋体" w:cs="宋体"/><w:sz w:val="21"/><w:szCs w:val="21"/><w:lang w:val="en-US" w:eastAsia="zh-CN"/></w:rPr><w:t>在训练过程中容易遇到梯度消失和梯度爆炸的问题，尤其是在处理较长序列时，这导致模型难以有效捕捉长程依赖（long-term dependencies）。</w:t></w:r></w:p><w:p w14:paraId="19218E65"><w:pPr><w:keepNext w:val="0"/><w:keepLines w:val="0"/><w:pageBreakBefore w:val="0"/><w:widowControl w:val="0"/><w:numPr><w:ilvl w:val="1"/><w:numId w:val="1"/></w:numPr><w:kinsoku/><w:wordWrap/><w:overflowPunct/><w:topLinePunct w:val="0"/><w:autoSpaceDE/><w:autoSpaceDN/><w:bidi w:val="0"/><w:adjustRightInd/><w:snapToGrid/><w:spacing w:before="157" w:beforeLines="50" w:after="157" w:afterLines="50"/><w:ind w:left="-60" w:leftChars="0" w:firstLine="480" w:firstLineChars="0"/><w:textAlignment w:val="auto"/><w:rPr><w:rFonts w:hint="eastAsia" w:ascii="宋体" w:hAnsi="宋体" w:eastAsia="宋体" w:cs="宋体"/><w:b/><w:bCs/><w:sz w:val="21"/><w:szCs w:val="21"/><w:lang w:val="en-US" w:eastAsia="zh-CN"/></w:rPr></w:pPr><w:r><w:rPr><w:rFonts w:hint="eastAsia" w:ascii="宋体" w:hAnsi="宋体" w:eastAsia="宋体" w:cs="宋体"/><w:b/><w:bCs/><w:sz w:val="21"/><w:szCs w:val="21"/><w:lang w:val="en-US" w:eastAsia="zh-CN"/></w:rPr><w:t xml:space="preserve">LSTM </w:t></w:r></w:p><w:p w14:paraId="6E4F51E1"><w:pPr><w:keepNext w:val="0"/><w:keepLines w:val="0"/><w:pageBreakBefore w:val="0"/><w:widowControl w:val="0"/><w:numPr><w:ilvl w:val="0"/><w:numId w:val="0"/></w:numPr><w:kinsoku/><w:wordWrap/><w:overflowPunct/><w:topLinePunct w:val="0"/><w:autoSpaceDE/><w:autoSpaceDN/><w:bidi w:val="0"/><w:adjustRightInd/><w:snapToGrid/><w:spacing w:before="157" w:beforeLines="50" w:after="157" w:afterLines="50"/><w:ind w:left="0" w:firstLine="422" w:firstLineChars="200"/><w:textAlignment w:val="auto"/><w:rPr><w:rFonts w:hint="eastAsia" w:ascii="宋体" w:hAnsi="宋体" w:eastAsia="宋体" w:cs="宋体"/><w:sz w:val="21"/><w:szCs w:val="21"/><w:lang w:val="en-US" w:eastAsia="zh-CN"/></w:rPr></w:pPr><w:r><w:rPr><w:rFonts w:hint="eastAsia" w:ascii="宋体" w:hAnsi="宋体" w:eastAsia="宋体" w:cs="宋体"/><w:b/><w:bCs/><w:sz w:val="21"/><w:szCs w:val="21"/><w:lang w:val="en-US" w:eastAsia="zh-CN"/></w:rPr><w:t>定义：</w:t></w:r><w:r><w:rPr><w:rFonts w:hint="eastAsia" w:ascii="宋体" w:hAnsi="宋体" w:eastAsia="宋体" w:cs="宋体"/><w:sz w:val="21"/><w:szCs w:val="21"/><w:lang w:val="en-US" w:eastAsia="zh-CN"/></w:rPr><w:t>LSTM(Long Short-Term Memory)是一种特殊的RNN，通过引入门控机制解决了标准RNN 的梯度消失问题。LSTM在每个时间步骤引入了“记忆单元”来存储和操作信息，使它能够有效地处理长期依赖问题。</w:t></w:r></w:p><w:p w14:paraId="6F83CEA4"><w:pPr><w:keepNext w:val="0"/><w:keepLines w:val="0"/><w:pageBreakBefore w:val="0"/><w:widowControl w:val="0"/><w:kinsoku/><w:wordWrap/><w:overflowPunct/><w:topLinePunct w:val="0"/><w:autoSpaceDE/><w:autoSpaceDN/><w:bidi w:val="0"/><w:adjustRightInd/><w:snapToGrid/><w:spacing w:before="157" w:beforeLines="50" w:after="157" w:afterLines="50"/><w:ind w:left="0" w:firstLine="422" w:firstLineChars="200"/><w:textAlignment w:val="auto"/><w:rPr><w:rFonts w:hint="eastAsia" w:ascii="宋体" w:hAnsi="宋体" w:eastAsia="宋体" w:cs="宋体"/><w:sz w:val="21"/><w:szCs w:val="21"/><w:lang w:val="en-US" w:eastAsia="zh-CN"/></w:rPr></w:pPr><w:r><w:rPr><w:rFonts w:hint="eastAsia" w:ascii="宋体" w:hAnsi="宋体" w:eastAsia="宋体" w:cs="宋体"/><w:b/><w:bCs/><w:sz w:val="21"/><w:szCs w:val="21"/><w:lang w:val="en-US" w:eastAsia="zh-CN"/></w:rPr><w:t>原理：</w:t></w:r><w:r><w:rPr><w:rFonts w:hint="eastAsia" w:ascii="宋体" w:hAnsi="宋体" w:eastAsia="宋体" w:cs="宋体"/><w:sz w:val="21"/><w:szCs w:val="21"/><w:lang w:val="en-US" w:eastAsia="zh-CN"/></w:rPr><w:t xml:space="preserve">由三个门控机制组成：输入门控制新信息的引入，遗忘门控制信息的遗忘，输出门控制哪些信息从 LSTM 单元流出。这些门控机制通过选择性地保留、遗忘和输出信息，允许 </w:t></w:r><w:r><w:rPr><w:rFonts w:hint="eastAsia" w:ascii="宋体" w:hAnsi="宋体" w:eastAsia="宋体" w:cs="宋体"/><w:b w:val="0"/><w:bCs w:val="0"/><w:sz w:val="21"/><w:szCs w:val="21"/><w:lang w:val="en-US" w:eastAsia="zh-CN"/></w:rPr><w:t>LSTM</w:t></w:r><w:r><w:rPr><w:rFonts w:hint="eastAsia" w:ascii="宋体" w:hAnsi="宋体" w:eastAsia="宋体" w:cs="宋体"/><w:sz w:val="21"/><w:szCs w:val="21"/><w:lang w:val="en-US" w:eastAsia="zh-CN"/></w:rPr><w:t>有效地学习长期的依赖关系，并能适应较长时间的序列学习任务。</w:t></w:r></w:p><w:p w14:paraId="15B55EB9"><w:pPr><w:keepNext w:val="0"/><w:keepLines w:val="0"/><w:pageBreakBefore w:val="0"/><w:widowControl w:val="0"/><w:kinsoku/><w:wordWrap/><w:overflowPunct/><w:topLinePunct w:val="0"/><w:autoSpaceDE/><w:autoSpaceDN/><w:bidi w:val="0"/><w:adjustRightInd/><w:snapToGrid/><w:spacing w:before="157" w:beforeLines="50" w:after="157" w:afterLines="50"/><w:ind w:left="0" w:firstLine="422" w:firstLineChars="200"/><w:textAlignment w:val="auto"/><w:rPr><w:rFonts w:hint="eastAsia" w:ascii="宋体" w:hAnsi="宋体" w:eastAsia="宋体" w:cs="宋体"/><w:sz w:val="21"/><w:szCs w:val="21"/><w:lang w:val="en-US" w:eastAsia="zh-CN"/></w:rPr></w:pPr><w:r><w:rPr><w:rFonts w:hint="eastAsia" w:ascii="宋体" w:hAnsi="宋体" w:eastAsia="宋体" w:cs="宋体"/><w:b/><w:bCs/><w:sz w:val="21"/><w:szCs w:val="21"/><w:lang w:val="en-US" w:eastAsia="zh-CN"/></w:rPr><w:t>优点：</w:t></w:r><w:r><w:rPr><w:rFonts w:hint="eastAsia" w:ascii="宋体" w:hAnsi="宋体" w:eastAsia="宋体" w:cs="宋体"/><w:sz w:val="21"/><w:szCs w:val="21"/><w:lang w:val="en-US" w:eastAsia="zh-CN"/></w:rPr><w:t>被广泛用于处理长时间序列问题，例如文本生成、机器翻译等任务，比传统的RNN能更好地捕捉到长期依赖，避免了梯度消失问题。</w:t></w:r></w:p><w:p w14:paraId="34161EAD"><w:pPr><w:keepNext w:val="0"/><w:keepLines w:val="0"/><w:pageBreakBefore w:val="0"/><w:widowControl w:val="0"/><w:numPr><w:ilvl w:val="1"/><w:numId w:val="1"/></w:numPr><w:kinsoku/><w:wordWrap/><w:overflowPunct/><w:topLinePunct w:val="0"/><w:autoSpaceDE/><w:autoSpaceDN/><w:bidi w:val="0"/><w:adjustRightInd/><w:snapToGrid/><w:spacing w:before="157" w:beforeLines="50" w:after="157" w:afterLines="50"/><w:ind w:left="-60" w:leftChars="0" w:firstLine="480" w:firstLineChars="0"/><w:textAlignment w:val="auto"/><w:rPr><w:rFonts w:hint="eastAsia" w:ascii="宋体" w:hAnsi="宋体" w:eastAsia="宋体" w:cs="宋体"/><w:b/><w:bCs/><w:sz w:val="21"/><w:szCs w:val="21"/><w:lang w:val="en-US" w:eastAsia="zh-CN"/></w:rPr></w:pPr><w:r><w:rPr><w:rFonts w:hint="eastAsia" w:ascii="宋体" w:hAnsi="宋体" w:eastAsia="宋体" w:cs="宋体"/><w:b/><w:bCs/><w:sz w:val="21"/><w:szCs w:val="21"/><w:lang w:val="en-US" w:eastAsia="zh-CN"/></w:rPr><w:t xml:space="preserve">GRU </w:t></w:r></w:p><w:p w14:paraId="5F3E2693"><w:pPr><w:keepNext w:val="0"/><w:keepLines w:val="0"/><w:pageBreakBefore w:val="0"/><w:widowControl w:val="0"/><w:kinsoku/><w:wordWrap/><w:overflowPunct/><w:topLinePunct w:val="0"/><w:autoSpaceDE/><w:autoSpaceDN/><w:bidi w:val="0"/><w:adjustRightInd/><w:snapToGrid/><w:spacing w:before="157" w:beforeLines="50" w:after="157" w:afterLines="50"/><w:ind w:left="0" w:firstLine="422" w:firstLineChars="200"/><w:textAlignment w:val="auto"/><w:rPr><w:rFonts w:hint="eastAsia" w:ascii="宋体" w:hAnsi="宋体" w:eastAsia="宋体" w:cs="宋体"/><w:sz w:val="21"/><w:szCs w:val="21"/><w:lang w:val="en-US" w:eastAsia="zh-CN"/></w:rPr></w:pPr><w:r><w:rPr><w:rFonts w:hint="eastAsia" w:ascii="宋体" w:hAnsi="宋体" w:eastAsia="宋体" w:cs="宋体"/><w:b/><w:bCs/><w:sz w:val="21"/><w:szCs w:val="21"/><w:lang w:val="en-US" w:eastAsia="zh-CN"/></w:rPr><w:t>定义：</w:t></w:r><w:r><w:rPr><w:rFonts w:hint="eastAsia" w:ascii="宋体" w:hAnsi="宋体" w:eastAsia="宋体" w:cs="宋体"/><w:sz w:val="21"/><w:szCs w:val="21"/><w:lang w:val="en-US" w:eastAsia="zh-CN"/></w:rPr><w:t>GRU(Gated Recurrent Unit)是LSTM的一种变体，也用于处理序列数据。GRU结构较为简化，使用两个门控机制来控制信息流动，分别是更新门（Update Gate）和重置门（Reset Gate）。</w:t></w:r></w:p><w:p w14:paraId="2B60C366"><w:pPr><w:keepNext w:val="0"/><w:keepLines w:val="0"/><w:pageBreakBefore w:val="0"/><w:widowControl w:val="0"/><w:kinsoku/><w:wordWrap/><w:overflowPunct/><w:topLinePunct w:val="0"/><w:autoSpaceDE/><w:autoSpaceDN/><w:bidi w:val="0"/><w:adjustRightInd/><w:snapToGrid/><w:spacing w:before="157" w:beforeLines="50" w:after="157" w:afterLines="50"/><w:ind w:left="0" w:firstLine="422" w:firstLineChars="200"/><w:textAlignment w:val="auto"/><w:rPr><w:rFonts w:hint="eastAsia" w:ascii="宋体" w:hAnsi="宋体" w:eastAsia="宋体" w:cs="宋体"/><w:sz w:val="21"/><w:szCs w:val="21"/><w:lang w:val="en-US" w:eastAsia="zh-CN"/></w:rPr></w:pPr><w:r><w:rPr><w:rFonts w:hint="eastAsia" w:ascii="宋体" w:hAnsi="宋体" w:eastAsia="宋体" w:cs="宋体"/><w:b/><w:bCs/><w:sz w:val="21"/><w:szCs w:val="21"/><w:lang w:val="en-US" w:eastAsia="zh-CN"/></w:rPr><w:t>原理：</w:t></w:r><w:r><w:rPr><w:rFonts w:hint="eastAsia" w:ascii="宋体" w:hAnsi="宋体" w:eastAsia="宋体" w:cs="宋体"/><w:sz w:val="21"/><w:szCs w:val="21"/><w:lang w:val="en-US" w:eastAsia="zh-CN"/></w:rPr><w:t>更新门控制当前时刻的输入信息与前一时刻的记忆信息的结合程度。重置门决定当前输入与记忆状态的相关性，通常用于控制长期依赖的“遗忘”。GRU只使用两个门，因此计算量相对较小。</w:t></w:r></w:p><w:p w14:paraId="606043D4"><w:pPr><w:keepNext w:val="0"/><w:keepLines w:val="0"/><w:pageBreakBefore w:val="0"/><w:widowControl w:val="0"/><w:kinsoku/><w:wordWrap/><w:overflowPunct/><w:topLinePunct w:val="0"/><w:autoSpaceDE/><w:autoSpaceDN/><w:bidi w:val="0"/><w:adjustRightInd/><w:snapToGrid/><w:spacing w:before="157" w:beforeLines="50" w:after="157" w:afterLines="50"/><w:ind w:left="0" w:firstLine="422" w:firstLineChars="200"/><w:textAlignment w:val="auto"/><w:rPr><w:rFonts w:hint="eastAsia" w:ascii="宋体" w:hAnsi="宋体" w:eastAsia="宋体" w:cs="宋体"/><w:sz w:val="21"/><w:szCs w:val="21"/><w:lang w:val="en-US" w:eastAsia="zh-CN"/></w:rPr></w:pPr><w:r><w:rPr><w:rFonts w:hint="eastAsia" w:ascii="宋体" w:hAnsi="宋体" w:eastAsia="宋体" w:cs="宋体"/><w:b/><w:bCs/><w:sz w:val="21"/><w:szCs w:val="21"/><w:lang w:val="en-US" w:eastAsia="zh-CN"/></w:rPr><w:t>优点：</w:t></w:r><w:r><w:rPr><w:rFonts w:hint="eastAsia" w:ascii="宋体" w:hAnsi="宋体" w:eastAsia="宋体" w:cs="宋体"/><w:sz w:val="21"/><w:szCs w:val="21"/><w:lang w:val="en-US" w:eastAsia="zh-CN"/></w:rPr><w:t>GRU相对于LSTM具有较少的参数，但性能相似，计算上更加高效，适用于需要较高计算效率的场景。</w:t></w:r></w:p><w:p w14:paraId="0E0EE62A"><w:pPr><w:keepNext w:val="0"/><w:keepLines w:val="0"/><w:pageBreakBefore w:val="0"/><w:widowControl w:val="0"/><w:kinsoku/><w:wordWrap/><w:overflowPunct/><w:topLinePunct w:val="0"/><w:autoSpaceDE/><w:autoSpaceDN/><w:bidi w:val="0"/><w:adjustRightInd/><w:snapToGrid/><w:spacing w:before="157" w:beforeLines="50" w:after="157" w:afterLines="50"/><w:ind w:left="0" w:firstLine="420" w:firstLineChars="200"/><w:textAlignment w:val="auto"/><w:rPr><w:rFonts w:hint="eastAsia" w:ascii="宋体" w:hAnsi="宋体" w:eastAsia="宋体" w:cs="宋体"/><w:sz w:val="21"/><w:szCs w:val="21"/><w:lang w:val="en-US" w:eastAsia="zh-CN"/></w:rPr></w:pPr></w:p><w:p w14:paraId="59E27E2D"><w:pPr><w:keepNext w:val="0"/><w:keepLines w:val="0"/><w:pageBreakBefore w:val="0"/><w:widowControl w:val="0"/><w:numPr><w:ilvl w:val="0"/><w:numId w:val="1"/></w:numPr><w:kinsoku/><w:wordWrap/><w:overflowPunct/><w:topLinePunct w:val="0"/><w:autoSpaceDE/><w:autoSpaceDN/><w:bidi w:val="0"/><w:adjustRightInd/><w:snapToGrid/><w:spacing w:before="157" w:beforeLines="50" w:after="157" w:afterLines="50"/><w:ind w:left="-480" w:leftChars="0" w:firstLine="480" w:firstLineChars="0"/><w:textAlignment w:val="auto"/><w:rPr><w:rFonts w:hint="eastAsia" w:ascii="宋体" w:hAnsi="宋体" w:eastAsia="宋体" w:cs="宋体"/><w:b/><w:bCs/><w:sz w:val="24"/><w:szCs w:val="24"/><w:lang w:val="en-US" w:eastAsia="zh-CN"/></w:rPr></w:pPr><w:r><w:rPr><w:rFonts w:hint="eastAsia" w:ascii="宋体" w:hAnsi="宋体" w:eastAsia="宋体" w:cs="宋体"/><w:b/><w:bCs/><w:sz w:val="24"/><w:szCs w:val="24"/><w:lang w:val="en-US" w:eastAsia="zh-CN"/></w:rPr><w:t>诗歌生成的过程</w:t></w:r></w:p><w:p w14:paraId="383DB118"><w:pPr><w:keepNext w:val="0"/><w:keepLines w:val="0"/><w:pageBreakBefore w:val="0"/><w:widowControl w:val="0"/><w:kinsoku/><w:wordWrap/><w:overflowPunct/><w:topLinePunct w:val="0"/><w:autoSpaceDE/><w:autoSpaceDN/><w:bidi w:val="0"/><w:adjustRightInd/><w:snapToGrid/><w:spacing w:before="157" w:beforeLines="50" w:after="157" w:afterLines="50"/><w:ind w:left="0" w:firstLine="420" w:firstLineChars="200"/><w:textAlignment w:val="auto"/><w:rPr><w:rFonts w:hint="eastAsia" w:ascii="宋体" w:hAnsi="宋体" w:eastAsia="宋体" w:cs="宋体"/><w:sz w:val="21"/><w:szCs w:val="21"/><w:lang w:val="en-US" w:eastAsia="zh-CN"/></w:rPr></w:pPr><w:r><w:rPr><w:rFonts w:hint="eastAsia" w:ascii="宋体" w:hAnsi="宋体" w:eastAsia="宋体" w:cs="宋体"/><w:sz w:val="21"/><w:szCs w:val="21"/><w:lang w:val="en-US" w:eastAsia="zh-CN"/></w:rPr><w:t>针对Pytorch版本可以分为几个主要步骤：</w:t></w:r></w:p><w:p w14:paraId="3316EF2B"><w:pPr><w:keepNext w:val="0"/><w:keepLines w:val="0"/><w:pageBreakBefore w:val="0"/><w:widowControl w:val="0"/><w:numPr><w:ilvl w:val="1"/><w:numId w:val="1"/></w:numPr><w:kinsoku/><w:wordWrap/><w:overflowPunct/><w:topLinePunct w:val="0"/><w:autoSpaceDE/><w:autoSpaceDN/><w:bidi w:val="0"/><w:adjustRightInd/><w:snapToGrid/><w:spacing w:before="157" w:beforeLines="50" w:after="157" w:afterLines="50"/><w:ind w:left="-60" w:leftChars="0" w:firstLine="480" w:firstLineChars="0"/><w:textAlignment w:val="auto"/><w:rPr><w:rFonts w:hint="eastAsia" w:ascii="宋体" w:hAnsi="宋体" w:eastAsia="宋体" w:cs="宋体"/><w:b/><w:bCs/><w:sz w:val="21"/><w:szCs w:val="21"/><w:lang w:val="en-US" w:eastAsia="zh-CN"/></w:rPr></w:pPr><w:r><w:rPr><w:rFonts w:hint="eastAsia" w:ascii="宋体" w:hAnsi="宋体" w:eastAsia="宋体" w:cs="宋体"/><w:b/><w:bCs/><w:sz w:val="21"/><w:szCs w:val="21"/><w:lang w:val="en-US" w:eastAsia="zh-CN"/></w:rPr><w:t>数据准备与预处理</w:t></w:r></w:p><w:p w14:paraId="1C33A3B4"><w:pPr><w:keepNext w:val="0"/><w:keepLines w:val="0"/><w:pageBreakBefore w:val="0"/><w:widowControl w:val="0"/><w:kinsoku/><w:wordWrap/><w:overflowPunct/><w:topLinePunct w:val="0"/><w:autoSpaceDE/><w:autoSpaceDN/><w:bidi w:val="0"/><w:adjustRightInd/><w:snapToGrid/><w:spacing w:before="157" w:beforeLines="50" w:after="157" w:afterLines="50"/><w:ind w:left="0" w:firstLine="420" w:firstLineChars="200"/><w:textAlignment w:val="auto"/><w:rPr><w:rFonts w:hint="eastAsia" w:ascii="宋体" w:hAnsi="宋体" w:eastAsia="宋体" w:cs="宋体"/><w:sz w:val="21"/><w:szCs w:val="21"/><w:lang w:val="en-US" w:eastAsia="zh-CN"/></w:rPr></w:pPr><w:r><w:rPr><w:rFonts w:hint="eastAsia" w:ascii="宋体" w:hAnsi="宋体" w:eastAsia="宋体" w:cs="宋体"/><w:sz w:val="21"/><w:szCs w:val="21"/><w:lang w:val="en-US" w:eastAsia="zh-CN"/></w:rPr><w:t>首先，对诗歌数据进行预处理：</w:t></w:r></w:p><w:p w14:paraId="4C49EBCE"><w:pPr><w:keepNext w:val="0"/><w:keepLines w:val="0"/><w:pageBreakBefore w:val="0"/><w:widowControl w:val="0"/><w:kinsoku/><w:wordWrap/><w:overflowPunct/><w:topLinePunct w:val="0"/><w:autoSpaceDE/><w:autoSpaceDN/><w:bidi w:val="0"/><w:adjustRightInd/><w:snapToGrid/><w:spacing w:before="157" w:beforeLines="50" w:after="157" w:afterLines="50"/><w:ind w:left="0" w:firstLine="420" w:firstLineChars="200"/><w:textAlignment w:val="auto"/><w:rPr><w:rFonts w:hint="eastAsia" w:ascii="宋体" w:hAnsi="宋体" w:eastAsia="宋体" w:cs="宋体"/><w:sz w:val="21"/><w:szCs w:val="21"/><w:lang w:val="en-US" w:eastAsia="zh-CN"/></w:rPr></w:pPr><w:r><w:rPr><w:rFonts w:hint="eastAsia" w:ascii="宋体" w:hAnsi="宋体" w:eastAsia="宋体" w:cs="宋体"/><w:sz w:val="21"/><w:szCs w:val="21"/><w:lang w:val="en-US" w:eastAsia="zh-CN"/></w:rPr><w:t>process_poems1和process_poems2：从poems.txt中加载诗歌，对每一首诗进行拆分，并将每个字转化为对应的索引，保存为二维数组 poems_vector。这样，每首诗就被表示为一个整数序列。</w:t></w:r></w:p><w:p w14:paraId="1DA444A2"><w:pPr><w:keepNext w:val="0"/><w:keepLines w:val="0"/><w:pageBreakBefore w:val="0"/><w:widowControl w:val="0"/><w:kinsoku/><w:wordWrap/><w:overflowPunct/><w:topLinePunct w:val="0"/><w:autoSpaceDE/><w:autoSpaceDN/><w:bidi w:val="0"/><w:adjustRightInd/><w:snapToGrid/><w:spacing w:before="157" w:beforeLines="50" w:after="157" w:afterLines="50"/><w:ind w:left="0" w:firstLine="420" w:firstLineChars="200"/><w:textAlignment w:val="auto"/><w:rPr><w:rFonts w:hint="eastAsia" w:ascii="宋体" w:hAnsi="宋体" w:eastAsia="宋体" w:cs="宋体"/><w:sz w:val="21"/><w:szCs w:val="21"/><w:lang w:val="en-US" w:eastAsia="zh-CN"/></w:rPr></w:pPr><w:r><w:rPr><w:rFonts w:hint="eastAsia" w:ascii="宋体" w:hAnsi="宋体" w:eastAsia="宋体" w:cs="宋体"/><w:sz w:val="21"/><w:szCs w:val="21"/><w:lang w:val="en-US" w:eastAsia="zh-CN"/></w:rPr><w:t>同时，我们为每首诗歌添加开始符号（start_token）和结束符号（end_token），以明确生成诗歌的开始与结束。</w:t></w:r></w:p><w:p w14:paraId="63C0EEDD"><w:pPr><w:keepNext w:val="0"/><w:keepLines w:val="0"/><w:pageBreakBefore w:val="0"/><w:widowControl w:val="0"/><w:numPr><w:ilvl w:val="1"/><w:numId w:val="1"/></w:numPr><w:kinsoku/><w:wordWrap/><w:overflowPunct/><w:topLinePunct w:val="0"/><w:autoSpaceDE/><w:autoSpaceDN/><w:bidi w:val="0"/><w:adjustRightInd/><w:snapToGrid/><w:spacing w:before="157" w:beforeLines="50" w:after="157" w:afterLines="50"/><w:ind w:left="-60" w:leftChars="0" w:firstLine="480" w:firstLineChars="0"/><w:textAlignment w:val="auto"/><w:rPr><w:rFonts w:hint="eastAsia" w:ascii="宋体" w:hAnsi="宋体" w:eastAsia="宋体" w:cs="宋体"/><w:b/><w:bCs/><w:sz w:val="21"/><w:szCs w:val="21"/><w:lang w:val="en-US" w:eastAsia="zh-CN"/></w:rPr></w:pPr><w:r><w:rPr><w:rFonts w:hint="eastAsia" w:ascii="宋体" w:hAnsi="宋体" w:eastAsia="宋体" w:cs="宋体"/><w:b/><w:bCs/><w:sz w:val="21"/><w:szCs w:val="21"/><w:lang w:val="en-US" w:eastAsia="zh-CN"/></w:rPr><w:t>构建RNN/LSTM模型</w:t></w:r></w:p><w:p w14:paraId="4219C23F"><w:pPr><w:keepNext w:val="0"/><w:keepLines w:val="0"/><w:pageBreakBefore w:val="0"/><w:widowControl w:val="0"/><w:kinsoku/><w:wordWrap/><w:overflowPunct/><w:topLinePunct w:val="0"/><w:autoSpaceDE/><w:autoSpaceDN/><w:bidi w:val="0"/><w:adjustRightInd/><w:snapToGrid/><w:spacing w:before="157" w:beforeLines="50" w:after="157" w:afterLines="50"/><w:ind w:left="0" w:firstLine="420" w:firstLineChars="200"/><w:textAlignment w:val="auto"/><w:rPr><w:rFonts w:hint="eastAsia" w:ascii="宋体" w:hAnsi="宋体" w:eastAsia="宋体" w:cs="宋体"/><w:sz w:val="21"/><w:szCs w:val="21"/><w:lang w:val="en-US" w:eastAsia="zh-CN"/></w:rPr></w:pPr><w:r><w:rPr><w:rFonts w:hint="eastAsia" w:ascii="宋体" w:hAnsi="宋体" w:eastAsia="宋体" w:cs="宋体"/><w:sz w:val="21"/><w:szCs w:val="21"/><w:lang w:val="en-US" w:eastAsia="zh-CN"/></w:rPr><w:t>使用RNN或LSTM模型来生成诗歌。模型包括以下几个部分：</w:t></w:r></w:p><w:p w14:paraId="385A47D3"><w:pPr><w:keepNext w:val="0"/><w:keepLines w:val="0"/><w:pageBreakBefore w:val="0"/><w:widowControl w:val="0"/><w:kinsoku/><w:wordWrap/><w:overflowPunct/><w:topLinePunct w:val="0"/><w:autoSpaceDE/><w:autoSpaceDN/><w:bidi w:val="0"/><w:adjustRightInd/><w:snapToGrid/><w:spacing w:before="157" w:beforeLines="50" w:after="157" w:afterLines="50"/><w:ind w:left="0" w:firstLine="420" w:firstLineChars="200"/><w:textAlignment w:val="auto"/><w:rPr><w:rFonts w:hint="eastAsia" w:ascii="宋体" w:hAnsi="宋体" w:eastAsia="宋体" w:cs="宋体"/><w:sz w:val="21"/><w:szCs w:val="21"/><w:lang w:val="en-US" w:eastAsia="zh-CN"/></w:rPr></w:pPr><w:r><w:rPr><w:rFonts w:hint="eastAsia" w:ascii="宋体" w:hAnsi="宋体" w:eastAsia="宋体" w:cs="宋体"/><w:sz w:val="21"/><w:szCs w:val="21"/><w:lang w:val="en-US" w:eastAsia="zh-CN"/></w:rPr><w:t>词嵌入层（Embedding Layer）：首先，输入的词索引将通过词嵌入层转化为稠密的向量表示，这些向量能够捕捉到词汇之间的语义关系。</w:t></w:r></w:p><w:p w14:paraId="74F261F5"><w:pPr><w:keepNext w:val="0"/><w:keepLines w:val="0"/><w:pageBreakBefore w:val="0"/><w:widowControl w:val="0"/><w:kinsoku/><w:wordWrap/><w:overflowPunct/><w:topLinePunct w:val="0"/><w:autoSpaceDE/><w:autoSpaceDN/><w:bidi w:val="0"/><w:adjustRightInd/><w:snapToGrid/><w:spacing w:before="157" w:beforeLines="50" w:after="157" w:afterLines="50"/><w:ind w:left="0" w:firstLine="420" w:firstLineChars="200"/><w:textAlignment w:val="auto"/><w:rPr><w:rFonts w:hint="eastAsia" w:ascii="宋体" w:hAnsi="宋体" w:eastAsia="宋体" w:cs="宋体"/><w:sz w:val="21"/><w:szCs w:val="21"/><w:lang w:val="en-US" w:eastAsia="zh-CN"/></w:rPr></w:pPr><w:r><w:rPr><w:rFonts w:hint="eastAsia" w:ascii="宋体" w:hAnsi="宋体" w:eastAsia="宋体" w:cs="宋体"/><w:sz w:val="21"/><w:szCs w:val="21"/><w:lang w:val="en-US" w:eastAsia="zh-CN"/></w:rPr><w:t>循环神经网络层（RNN/LSTM Layer）：接着，词嵌入向量被输入到RNN或LSTM网络中，网络通过其递归结构逐步处理序列数据，捕捉其中的时序依赖关系。</w:t></w:r></w:p><w:p w14:paraId="210D45B0"><w:pPr><w:keepNext w:val="0"/><w:keepLines w:val="0"/><w:pageBreakBefore w:val="0"/><w:widowControl w:val="0"/><w:kinsoku/><w:wordWrap/><w:overflowPunct/><w:topLinePunct w:val="0"/><w:autoSpaceDE/><w:autoSpaceDN/><w:bidi w:val="0"/><w:adjustRightInd/><w:snapToGrid/><w:spacing w:before="157" w:beforeLines="50" w:after="157" w:afterLines="50"/><w:ind w:left="0" w:firstLine="420" w:firstLineChars="200"/><w:textAlignment w:val="auto"/><w:rPr><w:rFonts w:hint="eastAsia" w:ascii="宋体" w:hAnsi="宋体" w:eastAsia="宋体" w:cs="宋体"/><w:sz w:val="21"/><w:szCs w:val="21"/><w:lang w:val="en-US" w:eastAsia="zh-CN"/></w:rPr></w:pPr><w:r><w:rPr><w:rFonts w:hint="eastAsia" w:ascii="宋体" w:hAnsi="宋体" w:eastAsia="宋体" w:cs="宋体"/><w:sz w:val="21"/><w:szCs w:val="21"/><w:lang w:val="en-US" w:eastAsia="zh-CN"/></w:rPr><w:t>全连接层（Fully Connected Layer）：LSTM网络的输出会被传入全连接层，将隐藏层状态映射到词汇空间中，生成下一步词汇的概率分布。</w:t></w:r></w:p><w:p w14:paraId="3B9A94E2"><w:pPr><w:keepNext w:val="0"/><w:keepLines w:val="0"/><w:pageBreakBefore w:val="0"/><w:widowControl w:val="0"/><w:kinsoku/><w:wordWrap/><w:overflowPunct/><w:topLinePunct w:val="0"/><w:autoSpaceDE/><w:autoSpaceDN/><w:bidi w:val="0"/><w:adjustRightInd/><w:snapToGrid/><w:spacing w:before="157" w:beforeLines="50" w:after="157" w:afterLines="50"/><w:ind w:left="0" w:firstLine="420" w:firstLineChars="200"/><w:textAlignment w:val="auto"/><w:rPr><w:rFonts w:hint="eastAsia" w:ascii="宋体" w:hAnsi="宋体" w:eastAsia="宋体" w:cs="宋体"/><w:sz w:val="21"/><w:szCs w:val="21"/><w:lang w:val="en-US" w:eastAsia="zh-CN"/></w:rPr></w:pPr><w:r><w:rPr><w:rFonts w:hint="eastAsia" w:ascii="宋体" w:hAnsi="宋体" w:eastAsia="宋体" w:cs="宋体"/><w:sz w:val="21"/><w:szCs w:val="21"/><w:lang w:val="en-US" w:eastAsia="zh-CN"/></w:rPr><w:t>训练过程中，模型通过反向传播算法（Backpropagation）调整参数，最小化生成的词汇与真实词汇之间的差距（通过负对数似然损失函数）。</w:t></w:r></w:p><w:p w14:paraId="6965DA11"><w:pPr><w:keepNext w:val="0"/><w:keepLines w:val="0"/><w:pageBreakBefore w:val="0"/><w:widowControl w:val="0"/><w:numPr><w:ilvl w:val="1"/><w:numId w:val="1"/></w:numPr><w:kinsoku/><w:wordWrap/><w:overflowPunct/><w:topLinePunct w:val="0"/><w:autoSpaceDE/><w:autoSpaceDN/><w:bidi w:val="0"/><w:adjustRightInd/><w:snapToGrid/><w:spacing w:before="157" w:beforeLines="50" w:after="157" w:afterLines="50"/><w:ind w:left="-60" w:leftChars="0" w:firstLine="480" w:firstLineChars="0"/><w:textAlignment w:val="auto"/><w:rPr><w:rFonts w:hint="eastAsia" w:ascii="宋体" w:hAnsi="宋体" w:eastAsia="宋体" w:cs="宋体"/><w:b/><w:bCs/><w:sz w:val="21"/><w:szCs w:val="21"/><w:lang w:val="en-US" w:eastAsia="zh-CN"/></w:rPr></w:pPr><w:r><w:rPr><w:rFonts w:hint="eastAsia" w:ascii="宋体" w:hAnsi="宋体" w:eastAsia="宋体" w:cs="宋体"/><w:b/><w:bCs/><w:sz w:val="21"/><w:szCs w:val="21"/><w:lang w:val="en-US" w:eastAsia="zh-CN"/></w:rPr><w:t>模型训练</w:t></w:r></w:p><w:p w14:paraId="1E15615B"><w:pPr><w:keepNext w:val="0"/><w:keepLines w:val="0"/><w:pageBreakBefore w:val="0"/><w:widowControl w:val="0"/><w:kinsoku/><w:wordWrap/><w:overflowPunct/><w:topLinePunct w:val="0"/><w:autoSpaceDE/><w:autoSpaceDN/><w:bidi w:val="0"/><w:adjustRightInd/><w:snapToGrid/><w:spacing w:before="157" w:beforeLines="50" w:after="157" w:afterLines="50"/><w:ind w:left="0" w:firstLine="420" w:firstLineChars="200"/><w:textAlignment w:val="auto"/><w:rPr><w:rFonts w:hint="eastAsia" w:ascii="宋体" w:hAnsi="宋体" w:eastAsia="宋体" w:cs="宋体"/><w:sz w:val="21"/><w:szCs w:val="21"/><w:lang w:val="en-US" w:eastAsia="zh-CN"/></w:rPr></w:pPr><w:r><w:rPr><w:rFonts w:hint="eastAsia" w:ascii="宋体" w:hAnsi="宋体" w:eastAsia="宋体" w:cs="宋体"/><w:sz w:val="21"/><w:szCs w:val="21"/><w:lang w:val="en-US" w:eastAsia="zh-CN"/></w:rPr><w:t>通过将诗歌数据集输入模型进行训练，模型逐渐学习诗歌的生成规律。</w:t></w:r></w:p><w:p w14:paraId="510DE486"><w:pPr><w:keepNext w:val="0"/><w:keepLines w:val="0"/><w:pageBreakBefore w:val="0"/><w:widowControl w:val="0"/><w:kinsoku/><w:wordWrap/><w:overflowPunct/><w:topLinePunct w:val="0"/><w:autoSpaceDE/><w:autoSpaceDN/><w:bidi w:val="0"/><w:adjustRightInd/><w:snapToGrid/><w:spacing w:before="157" w:beforeLines="50" w:after="157" w:afterLines="50"/><w:ind w:left="0" w:firstLine="420" w:firstLineChars="200"/><w:textAlignment w:val="auto"/><w:rPr><w:rFonts w:hint="eastAsia" w:ascii="宋体" w:hAnsi="宋体" w:eastAsia="宋体" w:cs="宋体"/><w:sz w:val="21"/><w:szCs w:val="21"/><w:lang w:val="en-US" w:eastAsia="zh-CN"/></w:rPr></w:pPr><w:r><w:rPr><w:rFonts w:hint="eastAsia" w:ascii="宋体" w:hAnsi="宋体" w:eastAsia="宋体" w:cs="宋体"/><w:sz w:val="21"/><w:szCs w:val="21"/><w:lang w:val="en-US" w:eastAsia="zh-CN"/></w:rPr><w:t>训练时，使用generate_batch函数将训练数据划分为多个batch，每个batch包含一组诗歌序列。</w:t></w:r></w:p><w:p w14:paraId="5BED810C"><w:pPr><w:keepNext w:val="0"/><w:keepLines w:val="0"/><w:pageBreakBefore w:val="0"/><w:widowControl w:val="0"/><w:kinsoku/><w:wordWrap/><w:overflowPunct/><w:topLinePunct w:val="0"/><w:autoSpaceDE/><w:autoSpaceDN/><w:bidi w:val="0"/><w:adjustRightInd/><w:snapToGrid/><w:spacing w:before="157" w:beforeLines="50" w:after="157" w:afterLines="50"/><w:ind w:left="0" w:firstLine="420" w:firstLineChars="200"/><w:textAlignment w:val="auto"/><w:rPr><w:rFonts w:hint="eastAsia" w:ascii="宋体" w:hAnsi="宋体" w:eastAsia="宋体" w:cs="宋体"/><w:sz w:val="21"/><w:szCs w:val="21"/><w:lang w:val="en-US" w:eastAsia="zh-CN"/></w:rPr></w:pPr><w:r><w:rPr><w:rFonts w:hint="eastAsia" w:ascii="宋体" w:hAnsi="宋体" w:eastAsia="宋体" w:cs="宋体"/><w:sz w:val="21"/><w:szCs w:val="21"/><w:lang w:val="en-US" w:eastAsia="zh-CN"/></w:rPr><w:t>在每个epoch训练中，我们计算模型的损失并进行梯度更新，以提高模型生成准确性的能力。</w:t></w:r></w:p><w:p w14:paraId="72788A96"><w:pPr><w:keepNext w:val="0"/><w:keepLines w:val="0"/><w:pageBreakBefore w:val="0"/><w:widowControl w:val="0"/><w:numPr><w:ilvl w:val="1"/><w:numId w:val="1"/></w:numPr><w:kinsoku/><w:wordWrap/><w:overflowPunct/><w:topLinePunct w:val="0"/><w:autoSpaceDE/><w:autoSpaceDN/><w:bidi w:val="0"/><w:adjustRightInd/><w:snapToGrid/><w:spacing w:before="157" w:beforeLines="50" w:after="157" w:afterLines="50"/><w:ind w:left="-60" w:leftChars="0" w:firstLine="480" w:firstLineChars="0"/><w:textAlignment w:val="auto"/><w:rPr><w:rFonts w:hint="eastAsia" w:ascii="宋体" w:hAnsi="宋体" w:eastAsia="宋体" w:cs="宋体"/><w:b/><w:bCs/><w:sz w:val="21"/><w:szCs w:val="21"/><w:lang w:val="en-US" w:eastAsia="zh-CN"/></w:rPr></w:pPr><w:r><w:rPr><w:rFonts w:hint="eastAsia" w:ascii="宋体" w:hAnsi="宋体" w:eastAsia="宋体" w:cs="宋体"/><w:b/><w:bCs/><w:sz w:val="21"/><w:szCs w:val="21"/><w:lang w:val="en-US" w:eastAsia="zh-CN"/></w:rPr><w:t>诗歌生成</w:t></w:r></w:p><w:p w14:paraId="37DB2C5F"><w:pPr><w:keepNext w:val="0"/><w:keepLines w:val="0"/><w:pageBreakBefore w:val="0"/><w:widowControl w:val="0"/><w:kinsoku/><w:wordWrap/><w:overflowPunct/><w:topLinePunct w:val="0"/><w:autoSpaceDE/><w:autoSpaceDN/><w:bidi w:val="0"/><w:adjustRightInd/><w:snapToGrid/><w:spacing w:before="157" w:beforeLines="50" w:after="157" w:afterLines="50"/><w:ind w:left="0" w:firstLine="420" w:firstLineChars="200"/><w:textAlignment w:val="auto"/><w:rPr><w:rFonts w:hint="eastAsia" w:ascii="宋体" w:hAnsi="宋体" w:eastAsia="宋体" w:cs="宋体"/><w:sz w:val="21"/><w:szCs w:val="21"/><w:lang w:val="en-US" w:eastAsia="zh-CN"/></w:rPr></w:pPr><w:r><w:rPr><w:rFonts w:hint="eastAsia" w:ascii="宋体" w:hAnsi="宋体" w:eastAsia="宋体" w:cs="宋体"/><w:sz w:val="21"/><w:szCs w:val="21"/><w:lang w:val="en-US" w:eastAsia="zh-CN"/></w:rPr><w:t>训练完成后，就可以用模型来生成诗歌。gen_poem函数，对于给定一个起始字，模型会逐字预测并生成诗歌。生成的过程通常是：</w:t></w:r></w:p><w:p w14:paraId="7F723B9D"><w:pPr><w:keepNext w:val="0"/><w:keepLines w:val="0"/><w:pageBreakBefore w:val="0"/><w:widowControl w:val="0"/><w:kinsoku/><w:wordWrap/><w:overflowPunct/><w:topLinePunct w:val="0"/><w:autoSpaceDE/><w:autoSpaceDN/><w:bidi w:val="0"/><w:adjustRightInd/><w:snapToGrid/><w:spacing w:before="157" w:beforeLines="50" w:after="157" w:afterLines="50"/><w:ind w:left="0" w:firstLine="420" w:firstLineChars="200"/><w:textAlignment w:val="auto"/><w:rPr><w:rFonts w:hint="eastAsia" w:ascii="宋体" w:hAnsi="宋体" w:eastAsia="宋体" w:cs="宋体"/><w:sz w:val="21"/><w:szCs w:val="21"/><w:lang w:val="en-US" w:eastAsia="zh-CN"/></w:rPr></w:pPr><w:r><w:rPr><w:rFonts w:hint="eastAsia" w:ascii="宋体" w:hAnsi="宋体" w:eastAsia="宋体" w:cs="宋体"/><w:sz w:val="21"/><w:szCs w:val="21"/><w:lang w:val="en-US" w:eastAsia="zh-CN"/></w:rPr><w:t>输入起始词：用户提供一个起始词（如“日”、“山”等），作为生成诗歌的开头。</w:t></w:r></w:p><w:p w14:paraId="3BE5E24B"><w:pPr><w:keepNext w:val="0"/><w:keepLines w:val="0"/><w:pageBreakBefore w:val="0"/><w:widowControl w:val="0"/><w:kinsoku/><w:wordWrap/><w:overflowPunct/><w:topLinePunct w:val="0"/><w:autoSpaceDE/><w:autoSpaceDN/><w:bidi w:val="0"/><w:adjustRightInd/><w:snapToGrid/><w:spacing w:before="157" w:beforeLines="50" w:after="157" w:afterLines="50"/><w:ind w:left="0" w:firstLine="420" w:firstLineChars="200"/><w:textAlignment w:val="auto"/><w:rPr><w:rFonts w:hint="eastAsia" w:ascii="宋体" w:hAnsi="宋体" w:eastAsia="宋体" w:cs="宋体"/><w:sz w:val="21"/><w:szCs w:val="21"/><w:lang w:val="en-US" w:eastAsia="zh-CN"/></w:rPr></w:pPr><w:r><w:rPr><w:rFonts w:hint="eastAsia" w:ascii="宋体" w:hAnsi="宋体" w:eastAsia="宋体" w:cs="宋体"/><w:sz w:val="21"/><w:szCs w:val="21"/><w:lang w:val="en-US" w:eastAsia="zh-CN"/></w:rPr><w:t>逐步生成：模型根据当前输入的词和前面生成的词，预测下一个词，并将其作为新的输入继续生成。</w:t></w:r></w:p><w:p w14:paraId="1B6CD863"><w:pPr><w:keepNext w:val="0"/><w:keepLines w:val="0"/><w:pageBreakBefore w:val="0"/><w:widowControl w:val="0"/><w:kinsoku/><w:wordWrap/><w:overflowPunct/><w:topLinePunct w:val="0"/><w:autoSpaceDE/><w:autoSpaceDN/><w:bidi w:val="0"/><w:adjustRightInd/><w:snapToGrid/><w:spacing w:before="157" w:beforeLines="50" w:after="157" w:afterLines="50"/><w:ind w:left="0" w:firstLine="420" w:firstLineChars="200"/><w:textAlignment w:val="auto"/><w:rPr><w:rFonts w:hint="eastAsia" w:ascii="宋体" w:hAnsi="宋体" w:eastAsia="宋体" w:cs="宋体"/><w:sz w:val="21"/><w:szCs w:val="21"/><w:lang w:val="en-US" w:eastAsia="zh-CN"/></w:rPr></w:pPr><w:r><w:rPr><w:rFonts w:hint="eastAsia" w:ascii="宋体" w:hAnsi="宋体" w:eastAsia="宋体" w:cs="宋体"/><w:sz w:val="21"/><w:szCs w:val="21"/><w:lang w:val="en-US" w:eastAsia="zh-CN"/></w:rPr><w:t>结束符号：生成的诗歌会在遇到结束符号（end_token）或生成的诗歌长度达到最大限制时停止。</w:t></w:r></w:p><w:p w14:paraId="1FAD00DE"><w:pPr><w:keepNext w:val="0"/><w:keepLines w:val="0"/><w:pageBreakBefore w:val="0"/><w:widowControl w:val="0"/><w:kinsoku/><w:wordWrap/><w:overflowPunct/><w:topLinePunct w:val="0"/><w:autoSpaceDE/><w:autoSpaceDN/><w:bidi w:val="0"/><w:adjustRightInd/><w:snapToGrid/><w:spacing w:before="157" w:beforeLines="50" w:after="157" w:afterLines="50"/><w:ind w:left="0" w:firstLine="420" w:firstLineChars="200"/><w:textAlignment w:val="auto"/><w:rPr><w:rFonts w:hint="eastAsia" w:ascii="宋体" w:hAnsi="宋体" w:eastAsia="宋体" w:cs="宋体"/><w:sz w:val="21"/><w:szCs w:val="21"/><w:lang w:val="en-US" w:eastAsia="zh-CN"/></w:rPr></w:pPr><w:r><w:rPr><w:rFonts w:hint="eastAsia" w:ascii="宋体" w:hAnsi="宋体" w:eastAsia="宋体" w:cs="宋体"/><w:sz w:val="21"/><w:szCs w:val="21"/><w:lang w:val="en-US" w:eastAsia="zh-CN"/></w:rPr><w:t>输出诗歌：生成完成后，pretty_print_poem格式化打印生成的诗歌。</w:t></w:r></w:p><w:p w14:paraId="69D16561"><w:pPr><w:keepNext w:val="0"/><w:keepLines w:val="0"/><w:pageBreakBefore w:val="0"/><w:widowControl w:val="0"/><w:kinsoku/><w:wordWrap/><w:overflowPunct/><w:topLinePunct w:val="0"/><w:autoSpaceDE/><w:autoSpaceDN/><w:bidi w:val="0"/><w:adjustRightInd/><w:snapToGrid/><w:spacing w:before="157" w:beforeLines="50" w:after="157" w:afterLines="50"/><w:ind w:left="0" w:firstLine="420" w:firstLineChars="200"/><w:textAlignment w:val="auto"/><w:rPr><w:rFonts w:hint="eastAsia" w:ascii="宋体" w:hAnsi="宋体" w:eastAsia="宋体" w:cs="宋体"/><w:sz w:val="21"/><w:szCs w:val="21"/><w:lang w:val="en-US" w:eastAsia="zh-CN"/></w:rPr></w:pPr><w:r><w:rPr><w:rFonts w:hint="eastAsia" w:ascii="宋体" w:hAnsi="宋体" w:eastAsia="宋体" w:cs="宋体"/><w:sz w:val="21"/><w:szCs w:val="21"/><w:lang w:val="en-US" w:eastAsia="zh-CN"/></w:rPr><w:t>通过这个生成过程，我们能够基于给定的起始词生成具有一定韵律和结构的诗句。</w:t></w:r></w:p><w:p w14:paraId="179A55A6"><w:pPr><w:keepNext w:val="0"/><w:keepLines w:val="0"/><w:pageBreakBefore w:val="0"/><w:widowControl w:val="0"/><w:kinsoku/><w:wordWrap/><w:overflowPunct/><w:topLinePunct w:val="0"/><w:autoSpaceDE/><w:autoSpaceDN/><w:bidi w:val="0"/><w:adjustRightInd/><w:snapToGrid/><w:spacing w:before="157" w:beforeLines="50" w:after="157" w:afterLines="50"/><w:ind w:left="0" w:firstLine="420" w:firstLineChars="200"/><w:textAlignment w:val="auto"/><w:rPr><w:rFonts w:hint="eastAsia" w:ascii="宋体" w:hAnsi="宋体" w:eastAsia="宋体" w:cs="宋体"/><w:sz w:val="21"/><w:szCs w:val="21"/><w:lang w:val="en-US" w:eastAsia="zh-CN"/></w:rPr></w:pPr></w:p><w:p w14:paraId="7D9AED22"><w:pPr><w:keepNext w:val="0"/><w:keepLines w:val="0"/><w:pageBreakBefore w:val="0"/><w:widowControl w:val="0"/><w:kinsoku/><w:wordWrap/><w:overflowPunct/><w:topLinePunct w:val="0"/><w:autoSpaceDE/><w:autoSpaceDN/><w:bidi w:val="0"/><w:adjustRightInd/><w:snapToGrid/><w:spacing w:before="157" w:beforeLines="50" w:after="157" w:afterLines="50"/><w:ind w:left="0" w:firstLine="420" w:firstLineChars="200"/><w:textAlignment w:val="auto"/><w:rPr><w:rFonts w:hint="eastAsia" w:ascii="宋体" w:hAnsi="宋体" w:eastAsia="宋体" w:cs="宋体"/><w:sz w:val="21"/><w:szCs w:val="21"/><w:lang w:val="en-US" w:eastAsia="zh-CN"/></w:rPr></w:pPr></w:p><w:p w14:paraId="583CE2A1"><w:pPr><w:keepNext w:val="0"/><w:keepLines w:val="0"/><w:pageBreakBefore w:val="0"/><w:widowControl w:val="0"/><w:numPr><w:ilvl w:val="0"/><w:numId w:val="1"/></w:numPr><w:kinsoku/><w:wordWrap/><w:overflowPunct/><w:topLinePunct w:val="0"/><w:autoSpaceDE/><w:autoSpaceDN/><w:bidi w:val="0"/><w:adjustRightInd/><w:snapToGrid/><w:spacing w:before="157" w:beforeLines="50" w:after="157" w:afterLines="50"/><w:ind w:left="-480" w:leftChars="0" w:firstLine="480" w:firstLineChars="0"/><w:textAlignment w:val="auto"/><w:rPr><w:rFonts w:hint="eastAsia" w:ascii="宋体" w:hAnsi="宋体" w:eastAsia="宋体" w:cs="宋体"/><w:b/><w:bCs/><w:sz w:val="24"/><w:szCs w:val="24"/><w:lang w:val="en-US" w:eastAsia="zh-CN"/></w:rPr></w:pPr><w:r><w:rPr><w:rFonts w:hint="eastAsia" w:ascii="宋体" w:hAnsi="宋体" w:eastAsia="宋体" w:cs="宋体"/><w:b/><w:bCs/><w:sz w:val="24"/><w:szCs w:val="24"/><w:lang w:val="en-US" w:eastAsia="zh-CN"/></w:rPr><w:t>结果截图</w:t></w:r></w:p><w:p w14:paraId="07C75B46"><w:pPr><w:keepNext w:val="0"/><w:keepLines w:val="0"/><w:pageBreakBefore w:val="0"/><w:widowControl w:val="0"/><w:kinsoku/><w:wordWrap/><w:overflowPunct/><w:topLinePunct w:val="0"/><w:autoSpaceDE/><w:autoSpaceDN/><w:bidi w:val="0"/><w:adjustRightInd/><w:snapToGrid/><w:spacing w:before="157" w:beforeLines="50" w:after="157" w:afterLines="50"/><w:ind w:left="0" w:firstLine="420" w:firstLineChars="200"/><w:textAlignment w:val="auto"/><w:rPr><w:rFonts w:hint="eastAsia" w:ascii="宋体" w:hAnsi="宋体" w:eastAsia="宋体" w:cs="宋体"/><w:sz w:val="21"/><w:szCs w:val="21"/><w:lang w:val="en-US" w:eastAsia="zh-CN"/></w:rPr></w:pPr><w:r><w:rPr><w:rFonts w:hint="eastAsia" w:ascii="宋体" w:hAnsi="宋体" w:eastAsia="宋体" w:cs="宋体"/><w:sz w:val="21"/><w:szCs w:val="21"/><w:lang w:val="en-US" w:eastAsia="zh-CN"/></w:rPr><w:t>训练过程截图：</w:t></w:r></w:p><w:p w14:paraId="7912A301"><w:pPr><w:keepNext w:val="0"/><w:keepLines w:val="0"/><w:pageBreakBefore w:val="0"/><w:widowControl w:val="0"/><w:kinsoku/><w:wordWrap/><w:overflowPunct/><w:topLinePunct w:val="0"/><w:autoSpaceDE/><w:autoSpaceDN/><w:bidi w:val="0"/><w:adjustRightInd/><w:snapToGrid/><w:spacing w:before="157" w:beforeLines="50" w:after="157" w:afterLines="50"/><w:textAlignment w:val="auto"/><w:rPr><w:rFonts w:hint="eastAsia" w:ascii="宋体" w:hAnsi="宋体" w:eastAsia="宋体" w:cs="宋体"/><w:sz w:val="21"/><w:szCs w:val="21"/><w:lang w:val="en-US" w:eastAsia="zh-CN"/></w:rPr></w:pPr><w:r><w:rPr><w:rFonts w:hint="eastAsia" w:ascii="宋体" w:hAnsi="宋体" w:eastAsia="宋体" w:cs="宋体"/><w:sz w:val="21"/><w:szCs w:val="21"/></w:rPr><w:drawing><wp:inline distT="0" distB="0" distL="114300" distR="114300"><wp:extent cx="5269865" cy="2800985"/><wp:effectExtent l="0" t="0" r="635" b="5715"/><wp:docPr id="4" name="图片 4"/><wp:cNvGraphicFramePr><a:graphicFrameLocks xmlns:a="http://schemas.openxmlformats.org/drawingml/2006/main" noChangeAspect="1"/></wp:cNvGraphicFramePr><a:graphic xmlns:a="http://schemas.openxmlformats.org/drawingml/2006/main"><a:graphicData uri="http://schemas.openxmlformats.org/drawingml/2006/picture"><pic:pic xmlns:pic="http://schemas.openxmlformats.org/drawingml/2006/picture"><pic:nvPicPr><pic:cNvPr id="4" name="图片 4"/><pic:cNvPicPr><a:picLocks noChangeAspect="1"/></pic:cNvPicPr></pic:nvPicPr><pic:blipFill><a:blip r:embed="rId4"/><a:stretch><a:fillRect/></a:stretch></pic:blipFill><pic:spPr><a:xfrm><a:off x="0" y="0"/><a:ext cx="5269865" cy="2800985"/></a:xfrm><a:prstGeom prst="rect"><a:avLst/></a:prstGeom><a:noFill/><a:ln><a:noFill/></a:ln></pic:spPr></pic:pic></a:graphicData></a:graphic></wp:inline></w:drawing></w:r><w:r><w:rPr><w:rFonts w:hint="eastAsia" w:ascii="宋体" w:hAnsi="宋体" w:eastAsia="宋体" w:cs="宋体"/><w:sz w:val="21"/><w:szCs w:val="21"/></w:rPr><w:drawing><wp:inline distT="0" distB="0" distL="114300" distR="114300"><wp:extent cx="5262245" cy="2152650"/><wp:effectExtent l="0" t="0" r="8255" b="6350"/><wp:docPr id="5" name="图片 5"/><wp:cNvGraphicFramePr><a:graphicFrameLocks xmlns:a="http://schemas.openxmlformats.org/drawingml/2006/main" noChangeAspect="1"/></wp:cNvGraphicFramePr><a:graphic xmlns:a="http://schemas.openxmlformats.org/drawingml/2006/main"><a:graphicData uri="http://schemas.openxmlformats.org/drawingml/2006/picture"><pic:pic xmlns:pic="http://schemas.openxmlformats.org/drawingml/2006/picture"><pic:nvPicPr><pic:cNvPr id="5" name="图片 5"/><pic:cNvPicPr><a:picLocks noChangeAspect="1"/></pic:cNvPicPr></pic:nvPicPr><pic:blipFill><a:blip r:embed="rId5"/><a:stretch><a:fillRect/></a:stretch></pic:blipFill><pic:spPr><a:xfrm><a:off x="0" y="0"/><a:ext cx="5262245" cy="2152650"/></a:xfrm><a:prstGeom prst="rect"><a:avLst/></a:prstGeom><a:noFill/><a:ln><a:noFill/></a:ln></pic:spPr></pic:pic></a:graphicData></a:graphic></wp:inline></w:drawing></w:r></w:p><w:p w14:paraId="22B346D4"><w:pPr><w:keepNext w:val="0"/><w:keepLines w:val="0"/><w:pageBreakBefore w:val="0"/><w:widowControl w:val="0"/><w:kinsoku/><w:wordWrap/><w:overflowPunct/><w:topLinePunct w:val="0"/><w:autoSpaceDE/><w:autoSpaceDN/><w:bidi w:val="0"/><w:adjustRightInd/><w:snapToGrid/><w:spacing w:before="157" w:beforeLines="50" w:after="157" w:afterLines="50"/><w:ind w:left="0" w:firstLine="420" w:firstLineChars="200"/><w:textAlignment w:val="auto"/><w:rPr><w:rFonts w:hint="eastAsia" w:ascii="宋体" w:hAnsi="宋体" w:eastAsia="宋体" w:cs="宋体"/><w:i w:val="0"/><w:iCs w:val="0"/><w:caps w:val="0"/><w:color w:val="1F2328"/><w:spacing w:val="0"/><w:sz w:val="21"/><w:szCs w:val="21"/><w:shd w:val="clear" w:fill="FFFFFF"/><w:lang w:eastAsia="zh-CN"/></w:rPr></w:pPr><w:r><w:rPr><w:rFonts w:hint="eastAsia" w:ascii="宋体" w:hAnsi="宋体" w:eastAsia="宋体" w:cs="宋体"/><w:i w:val="0"/><w:iCs w:val="0"/><w:caps w:val="0"/><w:color w:val="1F2328"/><w:spacing w:val="0"/><w:sz w:val="21"/><w:szCs w:val="21"/><w:shd w:val="clear" w:fill="FFFFFF"/></w:rPr><w:t>生成诗歌的结果</w:t></w:r><w:r><w:rPr><w:rFonts w:hint="eastAsia" w:ascii="宋体" w:hAnsi="宋体" w:eastAsia="宋体" w:cs="宋体"/><w:i w:val="0"/><w:iCs w:val="0"/><w:caps w:val="0"/><w:color w:val="1F2328"/><w:spacing w:val="0"/><w:sz w:val="21"/><w:szCs w:val="21"/><w:shd w:val="clear" w:fill="FFFFFF"/><w:lang w:eastAsia="zh-CN"/></w:rPr><w:t>：</w:t></w:r></w:p><w:p w14:paraId="247F7F76"><w:pPr><w:keepNext w:val="0"/><w:keepLines w:val="0"/><w:pageBreakBefore w:val="0"/><w:widowControl w:val="0"/><w:kinsoku/><w:wordWrap/><w:overflowPunct/><w:topLinePunct w:val="0"/><w:autoSpaceDE/><w:autoSpaceDN/><w:bidi w:val="0"/><w:adjustRightInd/><w:snapToGrid/><w:spacing w:before="157" w:beforeLines="50" w:after="157" w:afterLines="50"/><w:textAlignment w:val="auto"/><w:rPr><w:rFonts w:hint="eastAsia" w:ascii="宋体" w:hAnsi="宋体" w:eastAsia="宋体" w:cs="宋体"/><w:i w:val="0"/><w:iCs w:val="0"/><w:caps w:val="0"/><w:color w:val="1F2328"/><w:spacing w:val="0"/><w:sz w:val="21"/><w:szCs w:val="21"/><w:shd w:val="clear" w:fill="FFFFFF"/></w:rPr></w:pPr><w:r><w:drawing><wp:inline distT="0" distB="0" distL="114300" distR="114300"><wp:extent cx="5269865" cy="4539615"/><wp:effectExtent l="0" t="0" r="635" b="6985"/><wp:docPr id="1" name="图片 1"/><wp:cNvGraphicFramePr><a:graphicFrameLocks xmlns:a="http://schemas.openxmlformats.org/drawingml/2006/main" noChangeAspect="1"/></wp:cNvGraphicFramePr><a:graphic xmlns:a="http://schemas.openxmlformats.org/drawingml/2006/main"><a:graphicData uri="http://schemas.openxmlformats.org/drawingml/2006/picture"><pic:pic xmlns:pic="http://schemas.openxmlformats.org/drawingml/2006/picture"><pic:nvPicPr><pic:cNvPr id="1" name="图片 1"/><pic:cNvPicPr><a:picLocks noChangeAspect="1"/></pic:cNvPicPr></pic:nvPicPr><pic:blipFill><a:blip r:embed="rId6"/><a:stretch><a:fillRect/></a:stretch></pic:blipFill><pic:spPr><a:xfrm><a:off x="0" y="0"/><a:ext cx="5269865" cy="4539615"/></a:xfrm><a:prstGeom prst="rect"><a:avLst/></a:prstGeom><a:noFill/><a:ln><a:noFill/></a:ln></pic:spPr></pic:pic></a:graphicData></a:graphic></wp:inline></w:drawing></w:r><w:bookmarkStart w:id="0" w:name="_GoBack"/><w:bookmarkEnd w:id="0"/></w:p><w:p w14:paraId="2743C86C"><w:pPr><w:keepNext w:val="0"/><w:keepLines w:val="0"/><w:pageBreakBefore w:val="0"/><w:widowControl w:val="0"/><w:kinsoku/><w:wordWrap/><w:overflowPunct/><w:topLinePunct w:val="0"/><w:autoSpaceDE/><w:autoSpaceDN/><w:bidi w:val="0"/><w:adjustRightInd/><w:snapToGrid/><w:spacing w:before="157" w:beforeLines="50" w:after="157" w:afterLines="50"/><w:ind w:left="0" w:firstLine="420" w:firstLineChars="200"/><w:textAlignment w:val="auto"/><w:rPr><w:rFonts w:hint="eastAsia" w:ascii="宋体" w:hAnsi="宋体" w:eastAsia="宋体" w:cs="宋体"/><w:i w:val="0"/><w:iCs w:val="0"/><w:caps w:val="0"/><w:color w:val="1F2328"/><w:spacing w:val="0"/><w:sz w:val="21"/><w:szCs w:val="21"/><w:shd w:val="clear" w:fill="FFFFFF"/><w:lang w:val="en-US" w:eastAsia="zh-CN"/></w:rPr></w:pPr></w:p><w:p w14:paraId="0FAFA295"><w:pPr><w:keepNext w:val="0"/><w:keepLines w:val="0"/><w:pageBreakBefore w:val="0"/><w:widowControl w:val="0"/><w:numPr><w:ilvl w:val="0"/><w:numId w:val="1"/></w:numPr><w:kinsoku/><w:wordWrap/><w:overflowPunct/><w:topLinePunct w:val="0"/><w:autoSpaceDE/><w:autoSpaceDN/><w:bidi w:val="0"/><w:adjustRightInd/><w:snapToGrid/><w:spacing w:before="157" w:beforeLines="50" w:after="157" w:afterLines="50"/><w:ind w:left="-480" w:leftChars="0" w:firstLine="480" w:firstLineChars="0"/><w:textAlignment w:val="auto"/><w:rPr><w:rFonts w:hint="eastAsia" w:ascii="宋体" w:hAnsi="宋体" w:eastAsia="宋体" w:cs="宋体"/><w:b/><w:bCs/><w:sz w:val="24"/><w:szCs w:val="24"/><w:lang w:val="en-US" w:eastAsia="zh-CN"/></w:rPr></w:pPr><w:r><w:rPr><w:rFonts w:hint="eastAsia" w:ascii="宋体" w:hAnsi="宋体" w:eastAsia="宋体" w:cs="宋体"/><w:b/><w:bCs/><w:sz w:val="24"/><w:szCs w:val="24"/><w:lang w:val="en-US" w:eastAsia="zh-CN"/></w:rPr><w:t>实验总结</w:t></w:r></w:p><w:p w14:paraId="40BC1F28"><w:pPr><w:keepNext w:val="0"/><w:keepLines w:val="0"/><w:pageBreakBefore w:val="0"/><w:widowControl w:val="0"/><w:kinsoku/><w:wordWrap/><w:overflowPunct/><w:topLinePunct w:val="0"/><w:autoSpaceDE/><w:autoSpaceDN/><w:bidi w:val="0"/><w:adjustRightInd/><w:snapToGrid/><w:spacing w:before="157" w:beforeLines="50" w:after="157" w:afterLines="50"/><w:ind w:left="0" w:firstLine="420" w:firstLineChars="200"/><w:textAlignment w:val="auto"/><w:rPr><w:rFonts w:hint="eastAsia" w:ascii="宋体" w:hAnsi="宋体" w:eastAsia="宋体" w:cs="宋体"/><w:sz w:val="21"/><w:szCs w:val="21"/><w:lang w:val="en-US" w:eastAsia="zh-CN"/></w:rPr></w:pPr><w:r><w:rPr><w:rFonts w:hint="eastAsia" w:ascii="宋体" w:hAnsi="宋体" w:eastAsia="宋体" w:cs="宋体"/><w:sz w:val="21"/><w:szCs w:val="21"/><w:lang w:val="en-US" w:eastAsia="zh-CN"/></w:rPr><w:t>模型表现： 实验过程中LSTM模型表现出色，能够较好地捕捉诗歌的长时间依赖性，并生成具有一定韵律感的诗句。</w:t></w:r></w:p><w:p w14:paraId="4D19CC75"><w:pPr><w:keepNext w:val="0"/><w:keepLines w:val="0"/><w:pageBreakBefore w:val="0"/><w:widowControl w:val="0"/><w:kinsoku/><w:wordWrap/><w:overflowPunct/><w:topLinePunct w:val="0"/><w:autoSpaceDE/><w:autoSpaceDN/><w:bidi w:val="0"/><w:adjustRightInd/><w:snapToGrid/><w:spacing w:before="157" w:beforeLines="50" w:after="157" w:afterLines="50"/><w:ind w:left="0" w:firstLine="420" w:firstLineChars="200"/><w:textAlignment w:val="auto"/><w:rPr><w:rFonts w:hint="eastAsia" w:ascii="宋体" w:hAnsi="宋体" w:eastAsia="宋体" w:cs="宋体"/><w:sz w:val="21"/><w:szCs w:val="21"/><w:lang w:val="en-US" w:eastAsia="zh-CN"/></w:rPr></w:pPr><w:r><w:rPr><w:rFonts w:hint="eastAsia" w:ascii="宋体" w:hAnsi="宋体" w:eastAsia="宋体" w:cs="宋体"/><w:sz w:val="21"/><w:szCs w:val="21"/><w:lang w:val="en-US" w:eastAsia="zh-CN"/></w:rPr><w:t>训练过程： 在训练过程中，损失函数的值逐步减小，表示模型逐渐学会生成更符合诗歌结构的内容。但尽管如此，诗歌的生成仍存在一定的随机性，生成的诗句有时会出现不符合语法规则的情况。</w:t></w:r></w:p><w:p w14:paraId="1A42C605"><w:pPr><w:keepNext w:val="0"/><w:keepLines w:val="0"/><w:pageBreakBefore w:val="0"/><w:widowControl w:val="0"/><w:kinsoku/><w:wordWrap/><w:overflowPunct/><w:topLinePunct w:val="0"/><w:autoSpaceDE/><w:autoSpaceDN/><w:bidi w:val="0"/><w:adjustRightInd/><w:snapToGrid/><w:spacing w:before="157" w:beforeLines="50" w:after="157" w:afterLines="50"/><w:ind w:left="0" w:firstLine="420" w:firstLineChars="200"/><w:textAlignment w:val="auto"/><w:rPr><w:rFonts w:hint="eastAsia" w:ascii="宋体" w:hAnsi="宋体" w:eastAsia="宋体" w:cs="宋体"/><w:sz w:val="21"/><w:szCs w:val="21"/><w:lang w:val="en-US" w:eastAsia="zh-CN"/></w:rPr></w:pPr><w:r><w:rPr><w:rFonts w:hint="eastAsia" w:ascii="宋体" w:hAnsi="宋体" w:eastAsia="宋体" w:cs="宋体"/><w:sz w:val="21"/><w:szCs w:val="21"/><w:lang w:val="en-US" w:eastAsia="zh-CN"/></w:rPr><w:t>改进空间：可以进一步优化模型，采用更先进的生成模型，比如Transformer。可以采用更多的诗歌数据集进行训练，提升模型的鲁棒性和生成质量。可以试验其他的生成技巧，如温度控制、beam search等，以提高诗歌的多样性和质量。</w:t></w:r></w:p><w:sectPr><w:pgSz w:w="11906" w:h="16838"/><w:pgMar w:top="1440" w:right="1800" w:bottom="1440" w:left="1800" w:header="851" w:footer="992" w:gutter="0"/><w:cols w:space="425" w:num="1"/><w:docGrid w:type="lines" w:linePitch="312" w:charSpace="0"/></w:sectPr></w:body></w:document>